mrilong/__init__.py
mrilong/cli.py
mrilong/config.py
mrilong/infer.py
mrilong/io.py
mrilong/longitudinal.py
mrilong/mask.py
mrilong/metrics.py
mrilong/models.py
mrilong/paths.py
mrilong/preprocess.py
mrilong/registration.py
mrilong/roi.py
mrilong/tiling.py
mrilong/viz.py
mrilong/webapp.py
mrilong/MEDNet/G3D.py
mrilong/MEDNet/UNet3D.py
mrilong/MEDNet/UWaveViTNet3D.py
mrilong/MEDNet/__init__.py
mrilong/MEDNet/model_factory.py
mrilong/MEDNet/attentions/DWTSelfAttentionND.py
mrilong/MEDNet/attentions/WaveletViTND.py
mrilong/MEDNet/attentions/__init__.py
mrilong/MEDNet/bottlenecks/__init__.py
mrilong/MEDNet/bottlenecks/vanilla_bottleneck.py
mrilong/MEDNet/conv_systems/__init__.py
mrilong/MEDNet/conv_systems/vanilla_conv.py
mrilong/MEDNet/utils/DiceLossND.py
mrilong/MEDNet/utils/DiceMetricND.py
mrilong/MEDNet/utils/ZscoreNormalizeND.py
mrilong/MEDNet/utils/__init__.py
mrilong/MEDNet/webview/WebInteractivePlotInference.py
mrilong-0.0.2.dist-info/METADATA
mrilong-0.0.2.dist-info/WHEEL
mrilong-0.0.2.dist-info/licenses/LICENSE
mrilong-0.0.2.dist-info/RECORD
