Metadata-Version: 2.4
Name: MRILong
Version: 0.0.2
Summary: Longitudinal Analysis of Brain T1 MRI (3D) with Skull‑Strip and Tissue Segmentation
Project-URL: Homepage, https://github.com/multires-cv-graphs/MRILong
Project-URL: Issues, https://github.com/multires-cv-graphs/MRILong/issues
Author-email: Kishore Kumar Tarafdar <kishorektarafdar@gmail.com>
License-Expression: GPL-3.0-or-later
License-File: LICENSE
Classifier: Intended Audience :: Science/Research
Classifier: Operating System :: OS Independent
Classifier: Programming Language :: Python :: 3
Classifier: Topic :: Scientific/Engineering
Requires-Python: >=3.9
Requires-Dist: matplotlib>=3.10
Requires-Dist: nibabel>=5.0
Requires-Dist: numpy>=2.0
Requires-Dist: scipy>=1.10
Requires-Dist: tensorflow<2.20,>=2.15
Requires-Dist: tfdwt>=0.0.9
Provides-Extra: full
Requires-Dist: scikit-image>=0.21; extra == 'full'
Requires-Dist: simpleitk>=2.2; extra == 'full'
Provides-Extra: preproc
Requires-Dist: scikit-image>=0.21; extra == 'preproc'
Requires-Dist: simpleitk>=2.2; extra == 'preproc'
Provides-Extra: registration
Requires-Dist: simpleitk>=2.2; extra == 'registration'
